jupyter_pieces/__init__.py
jupyter_pieces/_version.py
jupyter_pieces/installation/__init__.py
jupyter_pieces/installation/helpers.py
jupyter_pieces/installation/installation_flow.py
jupyter_pieces-2.0.0.data/data/etc/jupyter/jupyter_server_config.d/jupyterlab_pieces.json
jupyter_pieces-2.0.0.data/data/share/jupyter/labextensions/jupyter_pieces/build_log.json
jupyter_pieces-2.0.0.data/data/share/jupyter/labextensions/jupyter_pieces/package.json
jupyter_pieces-2.0.0.data/data/share/jupyter/labextensions/jupyter_pieces/schemas/jupyter_pieces/package.json.orig
jupyter_pieces-2.0.0.data/data/share/jupyter/labextensions/jupyter_pieces/schemas/jupyter_pieces/pieces-settings.json
jupyter_pieces-2.0.0.data/data/share/jupyter/labextensions/jupyter_pieces/schemas/jupyter_pieces/plugin.json
jupyter_pieces-2.0.0.data/data/share/jupyter/labextensions/jupyter_pieces/static/030fa4d20748eb345e7c.png
jupyter_pieces-2.0.0.data/data/share/jupyter/labextensions/jupyter_pieces/static/0f6b671913b3ccf6492d.png
jupyter_pieces-2.0.0.data/data/share/jupyter/labextensions/jupyter_pieces/static/128d13b77e7afd44e6b5.png
jupyter_pieces-2.0.0.data/data/share/jupyter/labextensions/jupyter_pieces/static/1510db8818bb87ee222a.png
jupyter_pieces-2.0.0.data/data/share/jupyter/labextensions/jupyter_pieces/static/1b49f4243f28dc6fd72b.png
jupyter_pieces-2.0.0.data/data/share/jupyter/labextensions/jupyter_pieces/static/227f51ea56309b81891e.png
jupyter_pieces-2.0.0.data/data/share/jupyter/labextensions/jupyter_pieces/static/22966c232eb62852458d.png
jupyter_pieces-2.0.0.data/data/share/jupyter/labextensions/jupyter_pieces/static/23be88c1f57c57ea079d.png
jupyter_pieces-2.0.0.data/data/share/jupyter/labextensions/jupyter_pieces/static/2a0c94e8468f9954de15.png
jupyter_pieces-2.0.0.data/data/share/jupyter/labextensions/jupyter_pieces/static/2ad334b9305199ebd14e.png
jupyter_pieces-2.0.0.data/data/share/jupyter/labextensions/jupyter_pieces/static/2cbeadd9715665b92d7a.png
jupyter_pieces-2.0.0.dist-info/METADATA
jupyter_pieces-2.0.0.dist-info/WHEEL
jupyter_pieces-2.0.0.dist-info/licenses/LICENSE
jupyter_pieces-2.0.0.dist-info/RECORD
