Metadata-Version: 2.4
Name: jupyter_pieces
Version: 2.0.0
Dynamic: Keywords
Summary: Never forget again with Pieces: AI-powered workstream context awareness and material management
Project-URL: Homepage, https://old.docs.pieces.app/extensions-plugins/jupyterlab
Project-URL: Bug Tracker, https://github.com/pieces-app/support/issues
Project-URL: Repository, https://github.com/pieces-app/jupyter_pieces.git
Author-email: Pieces for Developers <support@pieces.app>
License-File: LICENSE
Classifier: Framework :: Jupyter
Classifier: Framework :: Jupyter :: JupyterLab
Classifier: Framework :: Jupyter :: JupyterLab :: 4
Classifier: Framework :: Jupyter :: JupyterLab :: Extensions
Classifier: Framework :: Jupyter :: JupyterLab :: Extensions :: Prebuilt
Classifier: License :: OSI Approved :: MIT License
Classifier: Programming Language :: Python
Classifier: Programming Language :: Python :: 3
Classifier: Programming Language :: Python :: 3.8
Classifier: Programming Language :: Python :: 3.9
Classifier: Programming Language :: Python :: 3.10
Classifier: Programming Language :: Python :: 3.11
Classifier: Programming Language :: Python :: 3.12
Requires-Python: >=3.8
Requires-Dist: jupyter-server<3,>=2.0.1
